app_min.py
nano_duration_py-0.1.0.dist-info/licenses/LICENSE
nano_duration_py-0.1.0.dist-info/METADATA
nano_duration_py-0.1.0.dist-info/WHEEL
nano_duration_py-0.1.0.dist-info/entry_points.txt
nano_duration_py-0.1.0.dist-info/top_level.txt
nano_duration_py-0.1.0.dist-info/RECORD
