Metadata-Version: 2.4
Name: nano-duration-py
Version: 0.1.0
Summary: Tiny h/m/s ↔ seconds converter in ~1KB (zero deps)
Author: ozgunlu
License: MIT
Project-URL: Homepage, https://github.com/ozgunlu/nano-duration
Project-URL: Issues, https://github.com/ozgunlu/nano-duration/issues
Requires-Python: >=3.8
License-File: LICENSE
Dynamic: license-file
